{"attributes":["Strike"],"block_number":5,"category":"Character","colors":["Red"],"cost":4,"counter":1000,"effect":"If you do not have a Character with a cost of 8 or more and a type including \"Whitebeard Pirates\", this Character gains -4000 power.<br>[Blocker] (After your opponent declares an attack, you may rest this card to make it the new target of the attack.)","id":"OP16-017","img_full_url":"https://www.onepiece-cardgame.com/images/cardlist/card/OP16-017.png?260518","img_url":"../images/cardlist/card/OP16-017.png?260518","name":"LittleOars Jr.","pack_id":"550116","power":8000,"rarity":"Rare","trigger":null,"types":["Giant","Whitebeard Pirates Allies"]}
